{
  "posts": [
    {
      "id": 1,
      "body": "# This is amazing!",
      "date": "2022-11-09T18:03:50.813Z"
    },
    {
      "id": 2,
      "body": "## This is amazing!",
      "date": "2022-10-08T17:43:43.442Z"
    },
    {
      "id": 2,
      "body": "> This is amazing!",
      "date": "2022-10-08T17:43:43.442Z"
    },
    {
      "id": 3,
      "body": "```javascript\nconsole.log('hello world')\n```",
      "date": "2022-10-08T17:43:43.442Z"
    },
    {
      "id": 4,
      "body": "Hey! `inline code`",
      "date": "2022-10-08T17:43:43.442Z"
    },
    {
      "id": 5,
      "body": "**testing divider!**\n\n---\n\nthis is a divider",
      "date": "2022-10-08T17:43:43.442Z"
    },
    {
      "id": 6,
      "body": "**testing lists!**\n\n---\n\n* this is a list\n* this is a list\n* this is a list",
      "date": "2022-10-08T17:43:43.442Z"
    },
    {
      "id": 7,
      "body": "**Let's test this thing *fully***\nThis is some code:\n```javascript\nconsole.log('hello world')\n```\nThis is a quote:\n>$$warning This is a quote  \n\nThis is an image: ![image](https://products.ls.graphics/mesh-gradients/images/02.-Egg-Sour-p-2600.jpeg)\nThis is a link: [link](https://google.com)\n",
      "date": "2022-10-08T17:43:43.442Z"
    },
    {
      "id": 8,
      "body": "```javascript\nconsole.log('hello world'); console.log('hello world'); console.log('hello world'); console.log('hello world') \n```",
      "date": "2022-10-08T17:43:43.442Z"
    },
    {
      "id": 9,
      "body": "jgufugifbhiugbfeuibg uifebgiu befg biufeb gijfebig bfe uibgoifeb giojfbegj befoijbgi foebi gbefij wjgob iefjbgoijfebw gijboij fbejigbef ijwbg jfiebg ijofebwejoigbji febgji bjigbfeijwbg jefibgijefboijgb ijefbgjifebj igbijefb gijfb jigbfj bjgib fjiwbg efjwi gjefwb gijfbfjieb ij befji $$opengraph https://valencassa.dev",
      "date": "2022-10-08T17:43:43.442Z"
    },
    {
      "body": "testing a new post!",
      "date": "2022-11-10T15:56:14.747Z",
      "id": 10
    }
  ],
  "views": {
    "views": 468
  }
}